jaxprvis/__init__.py
jaxprvis/jaxprvis.py
jaxprvis/math_util.py
jaxprvis/graph/__init__.py
jaxprvis/graph/graph.py
jaxprvis/graph/jaxpr_to_graph.py
jaxprvis/visualization/__init__.py
jaxprvis/visualization/display_assets.py
jaxprvis/visualization/physics.py
jaxprvis/visualization/simulation.py
jaxprvis-0.0.1.dist-info/LICENSE
jaxprvis-0.0.1.dist-info/METADATA
jaxprvis-0.0.1.dist-info/WHEEL
jaxprvis-0.0.1.dist-info/top_level.txt
jaxprvis-0.0.1.dist-info/RECORD
