Metadata-Version: 2.1
Name: jaxprvis
Version: 0.0.1
Summary: A visualizer for JaxPrs
Home-page: https://github.com/PSilvestre/jaxprvis
Author: Pedro F. Silvestre
Author-email: pmfsilvestre@gmail.com
Project-URL: Bug Tracker, https://github.com/PSilvestre/jaxprvis/issues
Classifier: Programming Language :: Python :: 3
Classifier: License :: OSI Approved :: GNU General Public License v3 (GPLv3)
Classifier: Operating System :: OS Independent
Requires-Python: >=3.8
License-File: LICENSE
Requires-Dist: jax (>=0.4.0)
Requires-Dist: jaxlib (>=0.4.0)
Requires-Dist: pygame (>=2.4.0)
Requires-Dist: numpy (>=1.24.0)
Provides-Extra: dev
Requires-Dist: pytest (>=7.2) ; extra == 'dev'
Requires-Dist: black (>=22.10) ; extra == 'dev'
Requires-Dist: ruff (>=0.0.263) ; extra == 'dev'
